mountain_project/__init__.py
mountain_project/mountain_project.py
mountain_project/requester.py
mountain_project-0.1.0.dist-info/LICENSE
mountain_project-0.1.0.dist-info/WHEEL
mountain_project-0.1.0.dist-info/METADATA
mountain_project-0.1.0.dist-info/RECORD
