Metadata-Version: 2.1
Name: mountain-project
Version: 0.1.0
Summary: Python MountainProject API Client
License: MIT
Author: Ben-Hu
Author-email: benjqh@gmail.com
Requires-Python: >=3.7,<4.0
Classifier: License :: OSI Approved :: MIT License
Classifier: Programming Language :: Python :: 3
Classifier: Programming Language :: Python :: 3.7
Classifier: Programming Language :: Python :: 3.8
Requires-Dist: requests (>=2.22.0,<3.0.0)
